zipit/__init__.py
zipit/cli.py
zipit_cli-1.0.0b1.dist-info/licenses/LICENSE
zipit_cli-1.0.0b1.dist-info/METADATA
zipit_cli-1.0.0b1.dist-info/WHEEL
zipit_cli-1.0.0b1.dist-info/entry_points.txt
zipit_cli-1.0.0b1.dist-info/top_level.txt
zipit_cli-1.0.0b1.dist-info/RECORD
