Metadata-Version: 2.4
Name: zipit-cli
Version: 1.0.0b1
Summary: A smart zip tool that respects .gitignore and custom patterns
Author: Zubin James
Author-email: zubinj.palit2002@gmail.com
Classifier: Programming Language :: Python :: 3
Classifier: License :: OSI Approved :: MIT License
Classifier: Operating System :: OS Independent
Requires-Python: >=3.7
License-File: LICENSE
Dynamic: author
Dynamic: author-email
Dynamic: classifier
Dynamic: description
Dynamic: description-content-type
Dynamic: license-file
Dynamic: requires-python
Dynamic: summary
